gg_cli/__init__.py
gg_cli/file.py
gg_cli/gg_main.py
gg_cli/llm.py
gg_cli-0.1.3.dist-info/METADATA
gg_cli-0.1.3.dist-info/WHEEL
gg_cli-0.1.3.dist-info/entry_points.txt
gg_cli-0.1.3.dist-info/RECORD
