Metadata-Version: 2.4
Name: gg-cli
Version: 0.1.3
Summary: Command-line agent
Requires-Python: >=3.12
Requires-Dist: appdirs>=1.4.4
Requires-Dist: openai>=1.102.0
Requires-Dist: requests>=2.32.5
